{
 "cnpj": "07.687.786\/0001-06",
 "fax": "9852-9323",
 "convenios": {
  "href": "http:\/\/api.convenios.gov.br\/siconv\/v1\/consulta\/convenios?id_proponente=7687786000106"
 },
 "cpf_responsavel": "***187846**",
 "empenhos": {
  "href": "http:\/\/api.convenios.gov.br\/siconv\/v1\/consulta\/empenhos?id_proponente_favorecido=7687786000106"
 },
 "nome": "ASSOCIACAO DOS CATADORES DE MATERIAIS RECICLAVEIS DE MATOZINHOS -ASMATOZ",
 "inscricao_estadual": "Isento",
 "esfera_administrativa": {
  "EsferaAdministrativa": {
   "href": "http:\/\/api.convenios.gov.br\/siconv\/id\/esfera_administrativa\/30",
   "id": 30
  }
 },
 "inscricao_municipal": "NÃO INFORMADO",
 "propostas": {
  "href": "http:\/\/api.convenios.gov.br\/siconv\/v1\/consulta\/propostas?id_proponente=7687786000106"
 },
 "habilitacoes": {
  "href": "http:\/\/api.convenios.gov.br\/siconv\/v1\/consulta\/habilitacoes_area_atuacao?id_proponente=7687786000106"
 },
 "href": "http:\/\/api.convenios.gov.br\/siconv\/id\/proponente\/7687786000106",
 "nome_responsavel": "MARLIDE ALVES ROCHA",
 "natureza_juridica": {
  "NaturezaJuridica": {
   "href": "http:\/\/api.convenios.gov.br\/siconv\/id\/natureza_juridica\/34",
   "id": 34
  }
 },
 "telefone": "(31)3712-5610",
 "cep": "35720000",
 "endereco": "RUA SAPUCAIA 31",
 "pessoa_responsavel": {
  "PessoaResponsavel": {
   "href": "http:\/\/api.convenios.gov.br\/siconv\/id\/pessoa_responsavel\/86DC7A82F98AFA40515D5F85501CE0020A54C356",
   "id": "86DC7A82F98AFA40515D5F85501CE0020A54C356"
  }
 },
 "id": 7687786000106,
 "municipio": {
  "Municipio": {
   "href": "http:\/\/api.convenios.gov.br\/siconv\/id\/municipio\/11797",
   "id": 11797
  }
 }
}
