{
 "cnpj": "07.876.517\/0001-98",
 "fax": "NÃO INFORMADO",
 "convenios": {
  "href": "http:\/\/api.convenios.gov.br\/siconv\/v1\/consulta\/convenios?id_proponente=7876517000198"
 },
 "cpf_responsavel": "***532466**",
 "empenhos": {
  "href": "http:\/\/api.convenios.gov.br\/siconv\/v1\/consulta\/empenhos?id_proponente_favorecido=7876517000198"
 },
 "nome": "ASSOCIACAO CENTRO DE REFERENCIA DA INFANCIA E PRESERVACAO DA VIDA - CASA GUARA",
 "inscricao_estadual": "isento",
 "esfera_administrativa": {
  "EsferaAdministrativa": {
   "href": "http:\/\/api.convenios.gov.br\/siconv\/id\/esfera_administrativa\/30",
   "id": 30
  }
 },
 "inscricao_municipal": "01804",
 "propostas": {
  "href": "http:\/\/api.convenios.gov.br\/siconv\/v1\/consulta\/propostas?id_proponente=7876517000198"
 },
 "habilitacoes": {
  "href": "http:\/\/api.convenios.gov.br\/siconv\/v1\/consulta\/habilitacoes_area_atuacao?id_proponente=7876517000198"
 },
 "href": "http:\/\/api.convenios.gov.br\/siconv\/id\/proponente\/7876517000198",
 "nome_responsavel": "JOSE CARLOS FERREIRA",
 "natureza_juridica": {
  "NaturezaJuridica": {
   "href": "http:\/\/api.convenios.gov.br\/siconv\/id\/natureza_juridica\/34",
   "id": 34
  }
 },
 "telefone": "031  3575-3464",
 "cep": "35460000",
 "endereco": "RUA SÃO SEBASTIÃO 56",
 "pessoa_responsavel": {
  "PessoaResponsavel": {
   "href": "http:\/\/api.convenios.gov.br\/siconv\/id\/pessoa_responsavel\/087006FA61F46638CA656D1B1B57D77BFC6F0641",
   "id": "087006FA61F46638CA656D1B1B57D77BFC6F0641"
  }
 },
 "id": 7876517000198,
 "municipio": {
  "Municipio": {
   "href": "http:\/\/api.convenios.gov.br\/siconv\/id\/municipio\/15681",
   "id": 15681
  }
 }
}
