{
 "cnpj": "10.586.338\/0001-20",
 "fax": "NÃO INFORMADO",
 "convenios": {
  "href": "http:\/\/api.convenios.gov.br\/siconv\/v1\/consulta\/convenios?id_proponente=10586338000120"
 },
 "cpf_responsavel": "***731506**",
 "empenhos": {
  "href": "http:\/\/api.convenios.gov.br\/siconv\/v1\/consulta\/empenhos?id_proponente_favorecido=10586338000120"
 },
 "nome": "INSTITUTO INICIATIVA GLOBAL",
 "inscricao_estadual": "NÃO INFORMADO",
 "esfera_administrativa": {
  "EsferaAdministrativa": {
   "href": "http:\/\/api.convenios.gov.br\/siconv\/id\/esfera_administrativa\/30",
   "id": 30
  }
 },
 "inscricao_municipal": "NÃO INFORMADO",
 "propostas": {
  "href": "http:\/\/api.convenios.gov.br\/siconv\/v1\/consulta\/propostas?id_proponente=10586338000120"
 },
 "habilitacoes": {
  "href": "http:\/\/api.convenios.gov.br\/siconv\/v1\/consulta\/habilitacoes_area_atuacao?id_proponente=10586338000120"
 },
 "href": "http:\/\/api.convenios.gov.br\/siconv\/id\/proponente\/10586338000120",
 "nome_responsavel": "WAGNER LUIS GONCALVES",
 "natureza_juridica": {
  "NaturezaJuridica": {
   "href": "http:\/\/api.convenios.gov.br\/siconv\/id\/natureza_juridica\/34",
   "id": 34
  }
 },
 "telefone": "31 98816234",
 "cep": "30170010",
 "endereco": "AV. BIAS FORTES 932 - SALA 305",
 "pessoa_responsavel": {
  "PessoaResponsavel": {
   "href": "http:\/\/api.convenios.gov.br\/siconv\/id\/pessoa_responsavel\/F4E8052956D57FEBDFE451AB7689673D18670B3F",
   "id": "F4E8052956D57FEBDFE451AB7689673D18670B3F"
  }
 },
 "id": 10586338000120,
 "municipio": {
  "Municipio": {
   "href": "http:\/\/api.convenios.gov.br\/siconv\/id\/municipio\/16100",
   "id": 16100
  }
 }
}
