{
 "cnpj": "73.542.367\/0001-00",
 "fax": "31 33725460",
 "convenios": {
  "href": "http:\/\/api.convenios.gov.br\/siconv\/v1\/consulta\/convenios?id_proponente=73542367000100"
 },
 "cpf_responsavel": "***965086**",
 "empenhos": {
  "href": "http:\/\/api.convenios.gov.br\/siconv\/v1\/consulta\/empenhos?id_proponente_favorecido=73542367000100"
 },
 "nome": "ASSOCIACAO BRASILEIRA DOS CRIADORES DO CAVALO PAMPA",
 "inscricao_estadual": "Isento",
 "esfera_administrativa": {
  "EsferaAdministrativa": {
   "href": "http:\/\/api.convenios.gov.br\/siconv\/id\/esfera_administrativa\/30",
   "id": 30
  }
 },
 "inscricao_municipal": "NÃO INFORMADO",
 "propostas": {
  "href": "http:\/\/api.convenios.gov.br\/siconv\/v1\/consulta\/propostas?id_proponente=73542367000100"
 },
 "habilitacoes": {
  "href": "http:\/\/api.convenios.gov.br\/siconv\/v1\/consulta\/habilitacoes_area_atuacao?id_proponente=73542367000100"
 },
 "href": "http:\/\/api.convenios.gov.br\/siconv\/id\/proponente\/73542367000100",
 "nome_responsavel": "AROLDO RODRIGUES DA SILVA",
 "natureza_juridica": {
  "NaturezaJuridica": {
   "href": "http:\/\/api.convenios.gov.br\/siconv\/id\/natureza_juridica\/34",
   "id": 34
  }
 },
 "telefone": "31 33722415",
 "cep": "30510000",
 "endereco": "AV. AMAZONAS 6020",
 "pessoa_responsavel": {
  "PessoaResponsavel": {
   "href": "http:\/\/api.convenios.gov.br\/siconv\/id\/pessoa_responsavel\/E4C3FEDF9DE2A8DDE67B18A3C21BAD45B051E350",
   "id": "E4C3FEDF9DE2A8DDE67B18A3C21BAD45B051E350"
  }
 },
 "id": 73542367000100,
 "municipio": {
  "Municipio": {
   "href": "http:\/\/api.convenios.gov.br\/siconv\/id\/municipio\/16100",
   "id": 16100
  }
 }
}
