{"metadados": {"total_registros": 19}, "situacoes_propostas": [{"href": "http://api.convenios.gov.br/siconv/id/situacao_proposta/60", "id": 60, "propostas": {"href": "http://api.convenios.gov.br/siconv/v1/consulta/propostas?id_situacao=60"}, "nome": "PROPOSTA/PLANO DE TRABALHO CADASTRADOS"}, {"href": "http://api.convenios.gov.br/siconv/id/situacao_proposta/61", "id": 61, "propostas": {"href": "http://api.convenios.gov.br/siconv/v1/consulta/propostas?id_situacao=61"}, "nome": "PROPOSTA/PLANO DE TRABALHO ENVIADO PARA AN\u00c1LISE"}, {"href": "http://api.convenios.gov.br/siconv/id/situacao_proposta/62", "id": 62, "propostas": {"href": "http://api.convenios.gov.br/siconv/v1/consulta/propostas?id_situacao=62"}, "nome": "PROPOSTA/PLANO DE TRABALHO EM AN\u00c1LISE"}, {"href": "http://api.convenios.gov.br/siconv/id/situacao_proposta/63", "id": 63, "propostas": {"href": "http://api.convenios.gov.br/siconv/v1/consulta/propostas?id_situacao=63"}, "nome": "PROPOSTA/PLANO DE TRABALHO EM COMPLEMENTA\u00c7\u00c3O"}, {"href": "http://api.convenios.gov.br/siconv/id/situacao_proposta/64", "id": 64, "propostas": {"href": "http://api.convenios.gov.br/siconv/v1/consulta/propostas?id_situacao=64"}, "nome": "PROPOSTA COMPLEMENTADA ENVIADA PARA AN\u00c1LISE"}, {"href": "http://api.convenios.gov.br/siconv/id/situacao_proposta/65", "id": 65, "propostas": {"href": "http://api.convenios.gov.br/siconv/v1/consulta/propostas?id_situacao=65"}, "nome": "PROPOSTA COMPLEMENTADA EM AN\u00c1LISE"}, {"href": "http://api.convenios.gov.br/siconv/id/situacao_proposta/67", "id": 67, "propostas": {"href": "http://api.convenios.gov.br/siconv/v1/consulta/propostas?id_situacao=67"}, "nome": "PROPOSTA APROVADA E PLANO DE TRABALHO EM AN\u00c1LISE"}, {"href": "http://api.convenios.gov.br/siconv/id/situacao_proposta/68", "id": 68, "propostas": {"href": "http://api.convenios.gov.br/siconv/v1/consulta/propostas?id_situacao=68"}, "nome": "PROPOSTA APROVADA E PLANO DE TRABALHO EM COMPLEMENTA\u00c7\u00c3O"}, {"href": "http://api.convenios.gov.br/siconv/id/situacao_proposta/69", "id": 69, "propostas": {"href": "http://api.convenios.gov.br/siconv/v1/consulta/propostas?id_situacao=69"}, "nome": "PROPOSTA APROVADA E PLANO DE TRABALHO COMPLEMENTADO ENVIADO PARA AN\u00c1LISE"}, {"href": "http://api.convenios.gov.br/siconv/id/situacao_proposta/70", "id": 70, "propostas": {"href": "http://api.convenios.gov.br/siconv/v1/consulta/propostas?id_situacao=70"}, "nome": "PROPOSTA APROVADA E PLANO DE TRABALHO COMPLEMENTADO EM AN\u00c1LISE"}, {"href": "http://api.convenios.gov.br/siconv/id/situacao_proposta/71", "id": 71, "propostas": {"href": "http://api.convenios.gov.br/siconv/v1/consulta/propostas?id_situacao=71"}, "nome": "PROPOSTA/PLANO DE TRABALHO APROVADOS"}, {"href": "http://api.convenios.gov.br/siconv/id/situacao_proposta/72", "id": 72, "propostas": {"href": "http://api.convenios.gov.br/siconv/v1/consulta/propostas?id_situacao=72"}, "nome": "PROPOSTA/PLANO DE TRABALHO CANCELADOS"}, {"href": "http://api.convenios.gov.br/siconv/id/situacao_proposta/73", "id": 73, "propostas": {"href": "http://api.convenios.gov.br/siconv/v1/consulta/propostas?id_situacao=73"}, "nome": "PROPOSTA/PLANO DE TRABALHO REJEITADOS"}, {"href": "http://api.convenios.gov.br/siconv/id/situacao_proposta/87", "id": 87, "propostas": {"href": "http://api.convenios.gov.br/siconv/v1/consulta/propostas?id_situacao=87"}, "nome": "PRESTA\u00c7\u00c3O DE CONTAS REJEITADA"}, {"href": "http://api.convenios.gov.br/siconv/id/situacao_proposta/88", "id": 88, "propostas": {"href": "http://api.convenios.gov.br/siconv/v1/consulta/propostas?id_situacao=88"}, "nome": "PRESTA\u00c7\u00c3O DE CONTAS APROVADA COM RESSALVAS"}, {"href": "http://api.convenios.gov.br/siconv/id/situacao_proposta/91", "id": 91, "propostas": {"href": "http://api.convenios.gov.br/siconv/v1/consulta/propostas?id_situacao=91"}, "nome": "ASSINATURA PENDENTE REGISTRO TV SIAFI"}, {"href": "http://api.convenios.gov.br/siconv/id/situacao_proposta/92", "id": 92, "propostas": {"href": "http://api.convenios.gov.br/siconv/v1/consulta/propostas?id_situacao=92"}, "nome": "CONV\u00caNIO ANULADO - ENCERRADO"}, {"href": "http://api.convenios.gov.br/siconv/id/situacao_proposta/96", "id": 96, "propostas": {"href": "http://api.convenios.gov.br/siconv/v1/consulta/propostas?id_situacao=96"}, "nome": "INADIMPLENTE"}, {"href": "http://api.convenios.gov.br/siconv/id/situacao_proposta/97", "id": 97, "propostas": {"href": "http://api.convenios.gov.br/siconv/v1/consulta/propostas?id_situacao=97"}, "nome": "PROPOSTA/PLANO DE TRABALHO REJEITADOS POR IMPEDIMENTO T\u00c9CNICO"}]}